python_email_sender/__init__.py
python_email_sender/utils.py
python_email_sender-0.0.4.dist-info/METADATA
python_email_sender-0.0.4.dist-info/WHEEL
python_email_sender-0.0.4.dist-info/top_level.txt
python_email_sender-0.0.4.dist-info/RECORD
