Metadata-Version: 2.1
Name: python-email-sender
Version: 0.0.4
Summary: Python package for sending email
Home-page: UNKNOWN
Author: Kwangryeol Park
Author-email: pkr7098@gmail.com
License: UNKNOWN
Platform: UNKNOWN
